llm_model_cost/__init__.py
llm_model_cost/calculator.py
llm_model_cost-1.0.0.dist-info/METADATA
llm_model_cost-1.0.0.dist-info/WHEEL
llm_model_cost-1.0.0.dist-info/top_level.txt
llm_model_cost-1.0.0.dist-info/RECORD
