Metadata-Version: 2.4
Name: llm_model_cost
Version: 1.0.0
Summary: A package to calculate token costs for LLM models
Home-page: https://github.com/Sukith-S/llm_model_cost
Author: SukithS
Author-email: sukith.sd2001@gmail.com
Classifier: Programming Language :: Python :: 3
Classifier: License :: OSI Approved :: MIT License
Classifier: Operating System :: OS Independent
Requires-Python: >=3.6
Requires-Dist: requests
Dynamic: author
Dynamic: author-email
Dynamic: classifier
Dynamic: description
Dynamic: description-content-type
Dynamic: home-page
Dynamic: requires-dist
Dynamic: requires-python
Dynamic: summary
